oszsave.py
oszsave-1.3.0.dist-info/METADATA
oszsave-1.3.0.dist-info/WHEEL
oszsave-1.3.0.dist-info/RECORD
