Metadata-Version: 2.1
Name: oszsave
Version: 1.3.0
Summary: A powerful osu map downloader
License: GPL v3
Author: forgedcore8
Requires-Python: >=3.11,<4.0
Classifier: License :: Other/Proprietary License
Classifier: Programming Language :: Python :: 3
Classifier: Programming Language :: Python :: 3.11
Requires-Dist: colorama (>=0.4.6,<0.5.0)
Requires-Dist: httpx (>=0.24.1,<0.25.0)
Requires-Dist: selenium (>=4.11.2,<5.0.0)
Requires-Dist: tqdm (>=4.65.2,<5.0.0)
